{
    "warehouse_stock": [
        {
            "warehouse_id": "WH-02  ",
            "sku": "ERP--KEY--005--2024",
            "product_name": "  Apple iPad Pro 12.9 512GB  ",
            "quantity_available": "12 units",
            "minimum_level": "28",
            "location": "Warehouse A - Section 1",
            "last_updated": "27/09/2025",
            "supplier": "Logitech International"
        },
        {
            "warehouse_id": "  WH-03  ",
            "sku": "ERP/LAP/001/2024",
            "product_name": "Logitech MX Keys  ",
            "quantity_available": "406 units",
            "minimum_level": "30",
            "location": "Warehouse B - Section 2",
            "last_updated": "08-09-2025 21:21:18",
            "supplier": "Apple Inc.  "
        },
        {
            "warehouse_id": "WH_02",
            "sku": "  ERP-MOU-006-2024",
            "product_name": "  Samsung Galaxy S24 Ultra  ",
            "quantity_available": "158",
            "minimum_level": "30",
            "location": "WAREHOUSE B - SECTION 2",
            "last_updated": "2025/09/19 19:23",
            "supplier": "  Logitech International"
        },
        {
            "warehouse_id": "WH-05",
            "sku": "ERP_TAB_003_2024",
            "product_name": "Apple iPad Pro 12.9 512GB",
            "quantity_available": "143",
            "minimum_level": "50",
            "location": "WAREHOUSE A - SECTION 1",
            "last_updated": "2025-09-23T08:07:38Z",
            "supplier": "  LG Electronics"
        },
        {
            "warehouse_id": "  WH-01",
            "sku": "ERP/PHONE/002/2024",
            "product_name": "  Apple iPad Pro 12.9 512GB",
            "quantity_available": "372pcs",
            "minimum_level": "32",
            "location": "Warehouse B - Section 2",
            "last_updated": "01-09-2025 06:21:52",
            "supplier": "  Apple Inc.  "
        },
        {
            "warehouse_id": "WH_02",
            "sku": "ERP/PHONE/002/2024",
            "product_name": "  Logitech MX Master 3S",
            "quantity_available": "247pcs",
            "minimum_level": "18",
            "location": "Warehouse B - Section 2",
            "last_updated": "15/09/2025",
            "supplier": "  Apple Inc."
        },
        {
            "warehouse_id": "WH_02",
            "sku": "ERP/KEY/005/2024",
            "product_name": "  ASUS VivoBook 15 Laptop  ",
            "quantity_available": "301 units",
            "minimum_level": "30",
            "location": "Warehouse B - Section 2",
            "last_updated": "04/09/2025 17:33",
            "supplier": "  ASUS Inc  "
        },
        {
            "warehouse_id": "WH_05",
            "sku": "ERP/MOU/006/2024",
            "product_name": "LG UltraWide 34\" Monitor  ",
            "quantity_available": "288pcs",
            "minimum_level": "14",
            "location": "Warehouse B - Section 2",
            "last_updated": "12/09/2025",
            "supplier": "  ASUS Inc"
        },
        {
            "warehouse_id": "WH-01",
            "sku": "  ERP-LAP-001-2024  ",
            "product_name": "  Logitech MX Master 3S",
            "quantity_available": "317pcs",
            "minimum_level": "41",
            "location": "Warehouse A - Section 1",
            "last_updated": "17/09/2025",
            "supplier": "Logitech"
        },
        {
            "warehouse_id": "WH_05",
            "sku": "  ERP-MON-004-2024  ",
            "product_name": "ASUS VivoBook 15 Laptop  ",
            "quantity_available": "67 units",
            "minimum_level": "32",
            "location": "WAREHOUSE B - SECTION 2",
            "last_updated": "04/09/2025 14:20",
            "supplier": "  Logitech"
        },
        {
            "warehouse_id": "WH_02",
            "sku": "  ERP-KEY-005-2024",
            "product_name": "LG UltraWide 34\" Monitor  ",
            "quantity_available": "184",
            "minimum_level": "26",
            "location": "Warehouse B - Section 2",
            "last_updated": "2025-09-21T14:12:55Z",
            "supplier": "  LG Electronics  "
        },
        {
            "warehouse_id": "WH-05",
            "sku": "ERP--MOU--006--2024",
            "product_name": "  Logitech MX Master 3S",
            "quantity_available": "421pcs",
            "minimum_level": "33",
            "location": "WAREHOUSE A - SECTION 1",
            "last_updated": "2025/10/06 19:01",
            "supplier": "Logitech International"
        },
        {
            "warehouse_id": "WH_03",
            "sku": "  ERP-LAP-001-2024  ",
            "product_name": "  Logitech MX Master 3S",
            "quantity_available": "118pcs",
            "minimum_level": "35",
            "location": "Warehouse A - Section 1",
            "last_updated": "07/09/2025 11:26",
            "supplier": "Logitech"
        },
        {
            "warehouse_id": "  WH-03  ",
            "sku": "ERP--LAP--001--2024",
            "product_name": "  Logitech MX Master 3S  ",
            "quantity_available": "75pcs",
            "minimum_level": "41",
            "location": "WAREHOUSE B - SECTION 2",
            "last_updated": "2025/09/24 14:31",
            "supplier": "  Apple Inc.  "
        },
        {
            "warehouse_id": "  WH-02  ",
            "sku": "ERP/MON/004/2024",
            "product_name": "  Logitech MX Keys  ",
            "quantity_available": "423 units",
            "minimum_level": "24",
            "location": "Warehouse B - Section 2",
            "last_updated": "13-09-2025 04:45:14",
            "supplier": "Logitech"
        },
        {
            "warehouse_id": "  WH-03",
            "sku": "ERP/MON/004/2024",
            "product_name": "ASUS VivoBook 15 Laptop  ",
            "quantity_available": "273pcs",
            "minimum_level": "16",
            "location": "Warehouse B - Section 2",
            "last_updated": "2025-09-02T22:00:54Z",
            "supplier": "  Apple Inc.  "
        },
        {
            "warehouse_id": "WH_03",
            "sku": "ERP-MOU-006-2024  ",
            "product_name": "Apple iPad Pro 12.9 512GB  ",
            "quantity_available": "6pcs",
            "minimum_level": "40",
            "location": "Warehouse B - Section 2",
            "last_updated": "2025/10/08 18:15",
            "supplier": "  Logitech International  "
        },
        {
            "warehouse_id": "WH-03",
            "sku": "ERP MOU 006 2024",
            "product_name": "Logitech MX Master 3S",
            "quantity_available": "305pcs",
            "minimum_level": "41",
            "location": "WAREHOUSE B - SECTION 2",
            "last_updated": "12/09/2025",
            "supplier": "Apple Inc."
        },
        {
            "warehouse_id": "WH_01",
            "sku": "  ERP-PHONE-002-2024  ",
            "product_name": "  LG UltraWide 34\" Monitor  ",
            "quantity_available": "245 units",
            "minimum_level": "39",
            "location": "Warehouse B - Section 2",
            "last_updated": "03/10/2025",
            "supplier": "Logitech"
        },
        {
            "warehouse_id": "WH-03",
            "sku": "ERP--TAB--003--2024",
            "product_name": "  Logitech MX Master 3S  ",
            "quantity_available": "442pcs",
            "minimum_level": "50",
            "location": "Warehouse B - Section 2",
            "last_updated": "21/09/2025 21:50",
            "supplier": "  Apple Inc.  "
        },
        {
            "warehouse_id": "  WH-03",
            "sku": "ERP_PHONE_002_2024",
            "product_name": "  Apple iPad Pro 12.9 512GB  ",
            "quantity_available": "52 units",
            "minimum_level": "17",
            "location": "WAREHOUSE A - SECTION 1",
            "last_updated": "07/10/2025",
            "supplier": "  Logitech"
        },
        {
            "warehouse_id": "WH_05",
            "sku": "ERP-TAB-003-2024",
            "product_name": "Logitech MX Keys",
            "quantity_available": "386pcs",
            "minimum_level": "15",
            "location": "WAREHOUSE A - SECTION 1",
            "last_updated": "2025-09-29T10:33:36Z",
            "supplier": "Apple Inc.  "
        },
        {
            "warehouse_id": "  WH-03  ",
            "sku": "ERP KEY 005 2024",
            "product_name": "Logitech MX Keys",
            "quantity_available": "400pcs",
            "minimum_level": "15",
            "location": "WAREHOUSE B - SECTION 2",
            "last_updated": "2025/10/07 23:59",
            "supplier": "Logitech"
        },
        {
            "warehouse_id": "WH-02",
            "sku": "ERP--TAB--003--2024",
            "product_name": "ASUS VivoBook 15 Laptop  ",
            "quantity_available": "385pcs",
            "minimum_level": "50",
            "location": "Warehouse B - Section 2",
            "last_updated": "2025-09-21T01:29:15Z",
            "supplier": "Logitech"
        },
        {
            "warehouse_id": "WH_01",
            "sku": "ERP--TAB--003--2024",
            "product_name": "Logitech MX Keys",
            "quantity_available": "77",
            "minimum_level": "39",
            "location": "Warehouse B - Section 2",
            "last_updated": "19/09/2025 14:20",
            "supplier": "  Logitech"
        },
        {
            "warehouse_id": "WH_01",
            "sku": "ERP-MOU-006-2024  ",
            "product_name": "LG UltraWide 34\" Monitor  ",
            "quantity_available": "169 units",
            "minimum_level": "46",
            "location": "Warehouse A - Section 1",
            "last_updated": "02/09/2025",
            "supplier": "  Logitech  "
        },
        {
            "warehouse_id": "WH-04",
            "sku": "ERP/PHONE/002/2024",
            "product_name": "Logitech MX Master 3S  ",
            "quantity_available": "116 units",
            "minimum_level": "24",
            "location": "WAREHOUSE A - SECTION 1",
            "last_updated": "2025/09/24 14:14",
            "supplier": "  Samsung Electronics"
        },
        {
            "warehouse_id": "WH_03",
            "sku": "ERP_MON_004_2024",
            "product_name": "Apple iPad Pro 12.9 512GB  ",
            "quantity_available": "236pcs",
            "minimum_level": "47",
            "location": "WAREHOUSE A - SECTION 1",
            "last_updated": "25/09/2025 17:25",
            "supplier": "Logitech International  "
        },
        {
            "warehouse_id": "WH_04",
            "sku": "ERP/MOU/006/2024",
            "product_name": "Logitech MX Keys  ",
            "quantity_available": "33 units",
            "minimum_level": "29",
            "location": "Warehouse A - Section 1",
            "last_updated": "08/09/2025",
            "supplier": "  Logitech International"
        },
        {
            "warehouse_id": "WH-02",
            "sku": "ERP TAB 003 2024",
            "product_name": "Logitech MX Master 3S  ",
            "quantity_available": "30pcs",
            "minimum_level": "45",
            "location": "Warehouse B - Section 2",
            "last_updated": "22-09-2025 03:55:09",
            "supplier": "ASUS Inc  "
        },
        {
            "warehouse_id": "WH_04",
            "sku": "ERP--LAP--001--2024",
            "product_name": "ASUS VivoBook 15 Laptop  ",
            "quantity_available": "487 units",
            "minimum_level": "46",
            "location": "WAREHOUSE A - SECTION 1",
            "last_updated": "11/09/2025",
            "supplier": "Apple Inc.  "
        },
        {
            "warehouse_id": "WH-05  ",
            "sku": "ERP_PHONE_002_2024",
            "product_name": "  Apple iPad Pro 12.9 512GB  ",
            "quantity_available": "85pcs",
            "minimum_level": "30",
            "location": "Warehouse A - Section 1",
            "last_updated": "19-09-2025 09:18:00",
            "supplier": "  Samsung Electronics"
        },
        {
            "warehouse_id": "WH-04",
            "sku": "ERP_PHONE_002_2024",
            "product_name": "  Logitech MX Master 3S  ",
            "quantity_available": "354 units",
            "minimum_level": "24",
            "location": "Warehouse B - Section 2",
            "last_updated": "02-09-2025 07:21:24",
            "supplier": "ASUS Inc  "
        },
        {
            "warehouse_id": "WH_03",
            "sku": "ERP--MON--004--2024",
            "product_name": "Logitech MX Keys  ",
            "quantity_available": "206pcs",
            "minimum_level": "42",
            "location": "Warehouse A - Section 1",
            "last_updated": "2025-09-02T07:11:07Z",
            "supplier": "Apple Inc."
        },
        {
            "warehouse_id": "WH_03",
            "sku": "ERP_KEY_005_2024",
            "product_name": "  Logitech MX Master 3S  ",
            "quantity_available": "266pcs",
            "minimum_level": "27",
            "location": "WAREHOUSE B - SECTION 2",
            "last_updated": "2025/09/28 19:02",
            "supplier": "ASUS Inc"
        },
        {
            "warehouse_id": "WH-02",
            "sku": "ERP MON 004 2024",
            "product_name": "ASUS VivoBook 15 Laptop  ",
            "quantity_available": "297 units",
            "minimum_level": "49",
            "location": "WAREHOUSE B - SECTION 2",
            "last_updated": "2025/09/10 13:52",
            "supplier": "  Samsung Electronics  "
        },
        {
            "warehouse_id": "  WH-04",
            "sku": "ERP_MON_004_2024",
            "product_name": "  Apple iPad Pro 12.9 512GB  ",
            "quantity_available": "436",
            "minimum_level": "11",
            "location": "WAREHOUSE B - SECTION 2",
            "last_updated": "2025/10/03 23:56",
            "supplier": "  Logitech International"
        },
        {
            "warehouse_id": "  WH-02  ",
            "sku": "ERP MOU 006 2024",
            "product_name": "Logitech MX Keys  ",
            "quantity_available": "481pcs",
            "minimum_level": "20",
            "location": "Warehouse B - Section 2",
            "last_updated": "2025/09/20 14:50",
            "supplier": "  Apple Inc.  "
        },
        {
            "warehouse_id": "WH-02",
            "sku": "  ERP-MOU-006-2024  ",
            "product_name": "LG UltraWide 34\" Monitor  ",
            "quantity_available": "192",
            "minimum_level": "27",
            "location": "Warehouse B - Section 2",
            "last_updated": "07-09-2025 06:16:18",
            "supplier": "ASUS Inc"
        },
        {
            "warehouse_id": "WH-05",
            "sku": "ERP_MON_004_2024",
            "product_name": "ASUS VivoBook 15 Laptop  ",
            "quantity_available": "176pcs",
            "minimum_level": "47",
            "location": "WAREHOUSE B - SECTION 2",
            "last_updated": "11/10/2025 09:44",
            "supplier": "  ASUS Inc"
        },
        {
            "warehouse_id": "WH-03",
            "sku": "ERP MON 004 2024",
            "product_name": "ASUS VivoBook 15 Laptop  ",
            "quantity_available": "155",
            "minimum_level": "25",
            "location": "WAREHOUSE B - SECTION 2",
            "last_updated": "18/09/2025 18:01",
            "supplier": "  LG Electronics"
        },
        {
            "warehouse_id": "WH-01",
            "sku": "ERP_MON_004_2024",
            "product_name": "  ASUS VivoBook 15 Laptop",
            "quantity_available": "248 units",
            "minimum_level": "19",
            "location": "WAREHOUSE A - SECTION 1",
            "last_updated": "07/09/2025 13:27",
            "supplier": "Samsung Electronics  "
        },
        {
            "warehouse_id": "  WH-04",
            "sku": "ERP--MOU--006--2024",
            "product_name": "LG UltraWide 34\" Monitor  ",
            "quantity_available": "18",
            "minimum_level": "34",
            "location": "Warehouse A - Section 1",
            "last_updated": "08-09-2025 17:08:06",
            "supplier": "Samsung Electronics  "
        },
        {
            "warehouse_id": "WH-05  ",
            "sku": "ERP_TAB_003_2024",
            "product_name": "LG UltraWide 34\" Monitor  ",
            "quantity_available": "419pcs",
            "minimum_level": "33",
            "location": "WAREHOUSE A - SECTION 1",
            "last_updated": "13-09-2025 10:07:04",
            "supplier": "Logitech International  "
        },
        {
            "warehouse_id": "WH-01",
            "sku": "ERP_KEY_005_2024",
            "product_name": "  LG UltraWide 34\" Monitor",
            "quantity_available": "79pcs",
            "minimum_level": "47",
            "location": "WAREHOUSE A - SECTION 1",
            "last_updated": "12-09-2025 01:04:21",
            "supplier": "  Logitech International"
        },
        {
            "warehouse_id": "WH_01",
            "sku": "ERP--PHONE--002--2024",
            "product_name": "  Logitech MX Keys  ",
            "quantity_available": "12 units",
            "minimum_level": "20",
            "location": "Warehouse B - Section 2",
            "last_updated": "06/09/2025",
            "supplier": "  LG Electronics  "
        },
        {
            "warehouse_id": "  WH-01  ",
            "sku": "  ERP-KEY-005-2024",
            "product_name": "Apple iPad Pro 12.9 512GB",
            "quantity_available": "6",
            "minimum_level": "17",
            "location": "WAREHOUSE A - SECTION 1",
            "last_updated": "06/10/2025",
            "supplier": "ASUS Inc"
        },
        {
            "warehouse_id": "  WH-03",
            "sku": "ERP PHONE 002 2024",
            "product_name": "Logitech MX Master 3S",
            "quantity_available": "32 units",
            "minimum_level": "13",
            "location": "Warehouse A - Section 1",
            "last_updated": "2025/09/14 06:13",
            "supplier": "Apple Inc.  "
        },
        {
            "warehouse_id": "  WH-03  ",
            "sku": "ERP_MOU_006_2024",
            "product_name": "  ASUS VivoBook 15 Laptop",
            "quantity_available": "44pcs",
            "minimum_level": "44",
            "location": "Warehouse A - Section 1",
            "last_updated": "2025/09/01 15:22",
            "supplier": "  Samsung Electronics"
        },
        {
            "warehouse_id": "WH-03",
            "sku": "ERP-MOU-006-2024",
            "product_name": "  Logitech MX Master 3S  ",
            "quantity_available": "272",
            "minimum_level": "25",
            "location": "WAREHOUSE A - SECTION 1",
            "last_updated": "12-09-2025 14:30:14",
            "supplier": "Samsung Electronics"
        },
        {
            "warehouse_id": "WH-02",
            "sku": "  ERP-PHONE-002-2024  ",
            "product_name": "Logitech MX Master 3S  ",
            "quantity_available": "12pcs",
            "minimum_level": "15",
            "location": "Warehouse B - Section 2",
            "last_updated": "03/09/2025",
            "supplier": "ASUS Inc"
        },
        {
            "warehouse_id": "WH-05  ",
            "sku": "ERP/MOU/006/2024",
            "product_name": "  LG UltraWide 34\" Monitor",
            "quantity_available": "42",
            "minimum_level": "11",
            "location": "Warehouse A - Section 1",
            "last_updated": "2025/09/17 04:15",
            "supplier": "  Logitech International"
        },
        {
            "warehouse_id": "WH_01",
            "sku": "ERP TAB 003 2024",
            "product_name": "  LG UltraWide 34\" Monitor  ",
            "quantity_available": "159",
            "minimum_level": "34",
            "location": "Warehouse B - Section 2",
            "last_updated": "05-10-2025 07:05:58",
            "supplier": "LG Electronics"
        },
        {
            "warehouse_id": "  WH-04  ",
            "sku": "  ERP-MON-004-2024  ",
            "product_name": "  Samsung Galaxy S24 Ultra  ",
            "quantity_available": "337pcs",
            "minimum_level": "10",
            "location": "Warehouse B - Section 2",
            "last_updated": "20-09-2025 17:19:01",
            "supplier": "  Samsung Electronics"
        },
        {
            "warehouse_id": "WH-01  ",
            "sku": "ERP-MON-004-2024  ",
            "product_name": "Logitech MX Keys",
            "quantity_available": "300pcs",
            "minimum_level": "17",
            "location": "Warehouse A - Section 1",
            "last_updated": "19-09-2025 22:35:48",
            "supplier": "  LG Electronics"
        },
        {
            "warehouse_id": "WH_01",
            "sku": "  ERP-MON-004-2024  ",
            "product_name": "Samsung Galaxy S24 Ultra",
            "quantity_available": "179",
            "minimum_level": "33",
            "location": "Warehouse A - Section 1",
            "last_updated": "2025/09/18 03:11",
            "supplier": "  Logitech International  "
        },
        {
            "warehouse_id": "  WH-04  ",
            "sku": "ERP--MOU--006--2024",
            "product_name": "  Logitech MX Keys",
            "quantity_available": "465",
            "minimum_level": "32",
            "location": "WAREHOUSE B - SECTION 2",
            "last_updated": "2025/09/12 14:45",
            "supplier": "Samsung Electronics  "
        },
        {
            "warehouse_id": "WH-04",
            "sku": "ERP_MOU_006_2024",
            "product_name": "Apple iPad Pro 12.9 512GB  ",
            "quantity_available": "110 units",
            "minimum_level": "49",
            "location": "Warehouse B - Section 2",
            "last_updated": "28/09/2025 11:19",
            "supplier": "  Logitech  "
        },
        {
            "warehouse_id": "WH-02",
            "sku": "  ERP-MOU-006-2024",
            "product_name": "  ASUS VivoBook 15 Laptop",
            "quantity_available": "69pcs",
            "minimum_level": "32",
            "location": "Warehouse B - Section 2",
            "last_updated": "22-09-2025 15:04:22",
            "supplier": "Apple Inc."
        },
        {
            "warehouse_id": "  WH-04",
            "sku": "ERP_MOU_006_2024",
            "product_name": "LG UltraWide 34\" Monitor  ",
            "quantity_available": "367",
            "minimum_level": "24",
            "location": "WAREHOUSE A - SECTION 1",
            "last_updated": "02-09-2025 20:53:26",
            "supplier": "  Logitech International"
        },
        {
            "warehouse_id": "WH-01",
            "sku": "ERP_PHONE_002_2024",
            "product_name": "Logitech MX Master 3S  ",
            "quantity_available": "32",
            "minimum_level": "35",
            "location": "Warehouse B - Section 2",
            "last_updated": "2025-09-11T04:23:02Z",
            "supplier": "Samsung Electronics  "
        },
        {
            "warehouse_id": "WH-05",
            "sku": "ERP MOU 006 2024",
            "product_name": "LG UltraWide 34\" Monitor",
            "quantity_available": "51 units",
            "minimum_level": "23",
            "location": "Warehouse A - Section 1",
            "last_updated": "01/10/2025",
            "supplier": "  Logitech  "
        },
        {
            "warehouse_id": "WH-04",
            "sku": "ERP_MOU_006_2024",
            "product_name": "Logitech MX Keys  ",
            "quantity_available": "93",
            "minimum_level": "10",
            "location": "Warehouse A - Section 1",
            "last_updated": "2025-09-10T00:49:55Z",
            "supplier": "Apple Inc."
        },
        {
            "warehouse_id": "  WH-01  ",
            "sku": "ERP_TAB_003_2024",
            "product_name": "  ASUS VivoBook 15 Laptop",
            "quantity_available": "439",
            "minimum_level": "26",
            "location": "Warehouse A - Section 1",
            "last_updated": "06/09/2025 16:22",
            "supplier": "Logitech"
        },
        {
            "warehouse_id": "WH-02",
            "sku": "ERP/MOU/006/2024",
            "product_name": "  Logitech MX Master 3S  ",
            "quantity_available": "369 units",
            "minimum_level": "46",
            "location": "WAREHOUSE A - SECTION 1",
            "last_updated": "19/09/2025 21:47",
            "supplier": "  Apple Inc.  "
        },
        {
            "warehouse_id": "WH-04",
            "sku": "ERP-TAB-003-2024",
            "product_name": "Logitech MX Keys",
            "quantity_available": "222pcs",
            "minimum_level": "23",
            "location": "WAREHOUSE A - SECTION 1",
            "last_updated": "29/09/2025 04:17",
            "supplier": "Apple Inc.  "
        },
        {
            "warehouse_id": "WH-05",
            "sku": "ERP/MON/004/2024",
            "product_name": "Logitech MX Keys  ",
            "quantity_available": "213 units",
            "minimum_level": "11",
            "location": "WAREHOUSE B - SECTION 2",
            "last_updated": "10/09/2025 12:22",
            "supplier": "  Apple Inc.  "
        },
        {
            "warehouse_id": "WH-01",
            "sku": "ERP--PHONE--002--2024",
            "product_name": "  Logitech MX Master 3S  ",
            "quantity_available": "162 units",
            "minimum_level": "26",
            "location": "Warehouse A - Section 1",
            "last_updated": "25/09/2025",
            "supplier": "  ASUS Inc  "
        },
        {
            "warehouse_id": "WH-02",
            "sku": "ERP--PHONE--002--2024",
            "product_name": "  LG UltraWide 34\" Monitor",
            "quantity_available": "198 units",
            "minimum_level": "26",
            "location": "Warehouse B - Section 2",
            "last_updated": "2025-09-30T15:58:06Z",
            "supplier": "Apple Inc."
        },
        {
            "warehouse_id": "WH-01",
            "sku": "ERP PHONE 002 2024",
            "product_name": "  Apple iPad Pro 12.9 512GB  ",
            "quantity_available": "336 units",
            "minimum_level": "39",
            "location": "WAREHOUSE A - SECTION 1",
            "last_updated": "2025-09-16T12:55:49Z",
            "supplier": "  LG Electronics  "
        }
    ]
}